MANIFEST.in
README.rst
setup.py
docs/__init__.py
docs/conf.py
docs/docs.py
dxl_pygate.egg-info/PKG-INFO
dxl_pygate.egg-info/SOURCES.txt
dxl_pygate.egg-info/dependency_links.txt
dxl_pygate.egg-info/entry_points.txt
dxl_pygate.egg-info/not-zip-safe
dxl_pygate.egg-info/requires.txt
dxl_pygate.egg-info/top_level.txt
pygate/__init__.py
pygate/cleaner.py
pygate/conf.py
pygate/config.py
pygate/config_maker.py
pygate/configs.py
pygate/initializer.py
pygate/merger.py
pygate/phantom.py
pygate/renderable.py
pygate/service.py
pygate/shell.py
pygate/submitter.py
pygate/utils.py
pygate/analysis/__init__.py
pygate/analysis/predifined.py
pygate/analysis/results.py
pygate/api/__init__.py
pygate/api/cli/__init__.py
pygate/api/cli/base.py
pygate/api/cli/commands.py
pygate/archive/__init__.py
pygate/cli/__init__.py
pygate/cli/analysis.py
pygate/cli/clean.py
pygate/cli/initialize.py
pygate/cli/mac_generate.py
pygate/cli/main.py
pygate/cli/merge.py
pygate/cli/submit.py
pygate/components/__init__.py
pygate/components/base.py
pygate/components/digitizer.py
pygate/components/misc.py
pygate/components/parameter.py
pygate/components/physics.py
pygate/components/simulation.py
pygate/components/source.py
pygate/components/utils.py
pygate/components/geometry/__init__.py
pygate/components/geometry/geometry.py
pygate/components/geometry/phantom.py
pygate/components/geometry/surface.py
pygate/components/geometry/volume.py
pygate/components/geometry/camera/__init__.py
pygate/components/geometry/camera/camera.py
pygate/components/geometry/camera/system.py
pygate/components/templates/simulation.j2
pygate/components/templates/test.j2
pygate/components/templates/utils.j2
pygate/components/templates/vec3.j2
pygate/components/templates/digitizer/coincidence_chain.j2
pygate/components/templates/digitizer/coincidence_sorter.j2
pygate/components/templates/digitizer/insertable.j2
pygate/components/templates/digitizer/singles/blurring.j2
pygate/components/templates/digitizer/singles/buffer.j2
pygate/components/templates/digitizer/singles/dead_time.j2
pygate/components/templates/digitizer/singles/holder.j2
pygate/components/templates/digitizer/singles/readout.j2
pygate/components/templates/digitizer/singles/singles.j2
