Metadata-Version: 1.0
Name: dxl-pygate
Version: 0.13.2
Summary: A simplified python interface for Gate.
Home-page: https://github.com/tech-pi/pygate
Author: Hong Xiang
Author-email: hx.hongxiang@gmail.com
License: MIT
Platform: UNKNOWN
